hcm2py/__init__.py
hcm2py/module_code.py
hcm2py-1.1.1.dist-info/METADATA
hcm2py-1.1.1.dist-info/WHEEL
hcm2py-1.1.1.dist-info/top_level.txt
hcm2py-1.1.1.dist-info/RECORD
