Metadata-Version: 2.1
Name: hcm2py
Version: 1.1.1
Summary: This is a registry generator for the Roblox game Circuit Maker 2
Author: Hawk King
Author-email: dbadbplayz@gmail.com
Keywords: registry,Circuit Maker 2,Roblox
Classifier: Programming Language :: Python :: 3
Classifier: Operating System :: OS Independent
Classifier: Intended Audience :: Developers
Requires-Python: >=3.6
Requires-Dist: pyperclip
Requires-Dist: requests
Requires-Dist: PyOpenGL
Requires-Dist: pygame
Requires-Dist: numpy
